git_big_picture/__init__.py
git_big_picture/__main__.py
git_big_picture/_main.py
git_big_picture-1.3.0.data/data/share/man/man1/git-big-picture.1
git_big_picture-1.3.0.dist-info/COPYING
git_big_picture-1.3.0.dist-info/METADATA
git_big_picture-1.3.0.dist-info/WHEEL
git_big_picture-1.3.0.dist-info/entry_points.txt
git_big_picture-1.3.0.dist-info/top_level.txt
git_big_picture-1.3.0.dist-info/RECORD
