Metadata-Version: 2.1
Name: git-big-picture
Version: 1.3.0
Summary: Git — the big picture
Home-page: https://github.com/git-big-picture/git-big-picture
Author: Sebastian Pipping, Julius Plenz, and Valentin Haenel
License: GPL v3 or later
Classifier: Programming Language :: Python :: 3
Classifier: Programming Language :: Python :: 3.8
Classifier: Programming Language :: Python :: 3.9
Classifier: Programming Language :: Python :: 3.10
Classifier: Programming Language :: Python :: 3.11
Classifier: Programming Language :: Python :: 3.12
Classifier: Programming Language :: Python :: 3 :: Only
Requires-Python: >=3.8
License-File: COPYING
Provides-Extra: tests
Requires-Dist: coverage ; extra == 'tests'
Requires-Dist: cram ; extra == 'tests'
Requires-Dist: parameterized ; extra == 'tests'
Requires-Dist: pytest ; extra == 'tests'
